setup.py
tapioca_enotas/__init__.py
tapioca_enotas/auth.py
tapioca_enotas/resource_mapping.py
tapioca_enotas/tapioca_enotas.py
tapioca_enotas.egg-info/PKG-INFO
tapioca_enotas.egg-info/SOURCES.txt
tapioca_enotas.egg-info/dependency_links.txt
tapioca_enotas.egg-info/not-zip-safe
tapioca_enotas.egg-info/requires.txt
tapioca_enotas.egg-info/top_level.txt