Metadata-Version: 1.1
Name: tapioca-enotas
Version: 0.2
Summary: enotas API wrapper using tapioca
Home-page: https://bitbucket.com/wpensar/tapioca_enotas
Author: Gustavo Hingel Morada
Author-email: gustavo.morada@wpensar.com.br
License: MIT
Keywords: enotas
Platform: UNKNOWN
Classifier: Development Status :: 5 - Production/Stable
Classifier: Intended Audience :: Developers
Classifier: License :: OSI Approved :: MIT License
Classifier: Natural Language :: English
Classifier: Programming Language :: Python :: 2
Classifier: Programming Language :: Python :: 2.7
Classifier: Programming Language :: Python :: 3
Classifier: Programming Language :: Python :: 3.1
Classifier: Programming Language :: Python :: 3.2
Classifier: Programming Language :: Python :: 3.3
Classifier: Programming Language :: Python :: 3.4
Classifier: Programming Language :: Python :: 3.5
